{
  "indexes": [
    {
      "collectionGroup": "returns",
      "queryScope": "COLLECTION",
      "fields": [
        {
          "fieldPath": "returnType",
          "order": "ASCENDING"
        },
        {
          "fieldPath": "returnDate",
          "order": "DESCENDING"
        },
        {
          "fieldPath": "__name__",
          "order": "DESCENDING"
        }
      ]
    },
    {
      "collectionGroup": "returns",
      "queryScope": "COLLECTION",
      "fields": [
        {
          "fieldPath": "customerId",
          "order": "ASCENDING"
        },
        {
          "fieldPath": "returnDate",
          "order": "DESCENDING"
        },
        {
          "fieldPath": "__name__",
          "order": "DESCENDING"
        }
      ]
    }
  ],
  "fieldOverrides": []
}
